margarita/__init__.py
margarita/cli.py
margarita/composer.py
margarita/parser.py
margarita/py.typed
margarita/renderer.py
margarita-0.3.3.dist-info/METADATA
margarita-0.3.3.dist-info/WHEEL
margarita-0.3.3.dist-info/entry_points.txt
margarita-0.3.3.dist-info/licenses/LICENSE
margarita-0.3.3.dist-info/RECORD
