Metadata-Version: 2.4
Name: margarita
Version: 0.3.3
Summary: A lightweight markup language and Python library for writing, composing, and rendering structured LLM prompts.
Project-URL: Homepage, https://github.com/Banyango/margarita
Project-URL: Documentation, https://banyango.github.io/margarita
Project-URL: Repository, https://github.com/Banyango/margarita
Project-URL: Issues, https://github.com/Banyango/margarita/issues
Project-URL: Changelog, https://github.com/Banyango/margarita/blob/main/CHANGELOG.md
Author-email: Kyle Reczek <kyle@banyango.com>
Maintainer-email: Kyle Reczek <kyle@banyango.com>
License: MIT
License-File: LICENSE
Keywords: llm,margarita,markup,prompt-engineering,templating
Classifier: Development Status :: 4 - Beta
Classifier: Intended Audience :: Developers
Classifier: License :: OSI Approved :: MIT License
Classifier: Operating System :: OS Independent
Classifier: Programming Language :: Python :: 3
Classifier: Programming Language :: Python :: 3.10
Classifier: Programming Language :: Python :: 3.11
Classifier: Programming Language :: Python :: 3.12
Classifier: Programming Language :: Python :: 3.13
Classifier: Programming Language :: Python :: 3.14
Classifier: Typing :: Typed
Requires-Python: <3.15,>=3.10
Requires-Dist: click>=8.0.0
Requires-Dist: loguru>=0.7.3
Requires-Dist: pyinstaller<7.0.0,>=6.18.0
Provides-Extra: dev
Requires-Dist: mypy>=1.8.0; extra == 'dev'
Requires-Dist: pre-commit>=3.6.0; extra == 'dev'
Requires-Dist: pytest-asyncio>=0.23.0; extra == 'dev'
Requires-Dist: pytest-cov>=4.1.0; extra == 'dev'
Requires-Dist: pytest>=8.0.0; extra == 'dev'
Requires-Dist: ruff>=0.1.0; extra == 'dev'
Provides-Extra: docs
Requires-Dist: mkdocs-material>=9.5.0; extra == 'docs'
Requires-Dist: mkdocs>=1.5.0; extra == 'docs'
Requires-Dist: mkdocstrings[python]>=0.24.0; extra == 'docs'
